ogpparser/__init__.py
ogpparser/ogpparser.py
ogpparser-1.0.4.dist-info/LICENSE
ogpparser-1.0.4.dist-info/METADATA
ogpparser-1.0.4.dist-info/WHEEL
ogpparser-1.0.4.dist-info/top_level.txt
ogpparser-1.0.4.dist-info/RECORD
