Metadata-Version: 2.1
Name: ogpparser
Version: 1.0.4
Summary: Open Graph Protocolのタグを取得
Home-page: https://github.com/reeve0930/ogpparser
Author: reeve0930
Author-email: reeve0930@gmail.com
License: MIT
Keywords: OGP OpenGraphProtocol parser
Platform: UNKNOWN
Classifier: License :: OSI Approved :: MIT License
Classifier: Programming Language :: Python :: 3.7
Classifier: Programming Language :: Python :: 3.6
Requires-Dist: beautifulsoup4
